tatb06_fft-0.2.dist-info/METADATA
tatb06_fft-0.2.dist-info/WHEEL
tatb06_fft-0.2.dist-info/licenses/LICENSE
tatb06_fft/__init__.py
tatb06_fft/_tatb06_fft.cpython-313-darwin.so
tatb06_fft/dft.py
tatb06_fft/fft.py
tatb06_fft/tools.py
tatb06_fft-0.2.dist-info/RECORD
